usr/share/applications/gdocs.desktop
usr/share/applications/msoo.desktop
usr/share/pixmaps/gdocs.svg
usr/share/pixmaps/msoo.svg
weboffice/__init__.py
weboffice/githosting.py
weboffice/progressbar.py
web_office-1.0.1.dist-info/LICENSE
web_office-1.0.1.dist-info/METADATA
web_office-1.0.1.dist-info/WHEEL
web_office-1.0.1.dist-info/entry_points.txt
web_office-1.0.1.dist-info/top_level.txt
web_office-1.0.1.dist-info/RECORD
