Metadata-Version: 2.1
Name: web-office
Version: 1.0.1
Summary: View office documents in browser using web services.
Home-page: https://gitlab.com/pacholik1/WebOffice
Author: Vojtěch Pachol
Author-email: pacholick@gmail.com
License: LGPL-3.0
Keywords: python,office
Platform: UNKNOWN
Classifier: Development Status :: 5 - Production/Stable
Classifier: Programming Language :: Python :: 3
Requires-Dist: GitPython
Requires-Dist: progresslib
